resolwe/__init__.py
resolwe/api_urls.py
resolwe/composer.py
resolwe/utils.py
resolwe/auditlog/__init__.py
resolwe/auditlog/apps.py
resolwe/auditlog/auditmanager.py
resolwe/auditlog/logger.py
resolwe/auditlog/middleware.py
resolwe/auditlog/models.py
resolwe/db/__init__.py
resolwe/db/postgresql/__init__.py
resolwe/db/postgresql/base.py
resolwe/flow/__init__.py
resolwe/flow/admin.py
resolwe/flow/apps.py
resolwe/flow/engine.py
resolwe/flow/exceptions.py
resolwe/flow/filters.py
resolwe/flow/finders.py
resolwe/flow/migration_ops.py
resolwe/flow/routing.py
resolwe/flow/signals.py
resolwe/flow/tasks.py
resolwe/flow/docker_images/Dockerfile.communication
resolwe/flow/docker_images/Readme.md
resolwe/flow/execution_engines/__init__.py
resolwe/flow/execution_engines/base.py
resolwe/flow/execution_engines/exceptions.py
resolwe/flow/execution_engines/bash/__init__.py
resolwe/flow/execution_engines/python/__init__.py
resolwe/flow/execution_engines/workflow/__init__.py
resolwe/flow/executors/__init__.py
resolwe/flow/executors/__main__.py
resolwe/flow/executors/constants.py
resolwe/flow/executors/global_settings.py
resolwe/flow/executors/init_container.py
resolwe/flow/executors/logger.py
resolwe/flow/executors/prepare.py
resolwe/flow/executors/protocol.py
resolwe/flow/executors/requirements.txt
resolwe/flow/executors/run.py
resolwe/flow/executors/socket_utils.py
resolwe/flow/executors/startup_communication_container.py
resolwe/flow/executors/startup_processing_container.py
resolwe/flow/executors/transfer.py
resolwe/flow/executors/zeromq_utils.py
resolwe/flow/executors/docker/__init__.py
resolwe/flow/executors/docker/prepare.py
resolwe/flow/executors/docker/run.py
resolwe/flow/executors/local/__init__.py
resolwe/flow/executors/local/prepare.py
resolwe/flow/executors/local/run.py
resolwe/flow/executors/null/__init__.py
resolwe/flow/executors/null/prepare.py
resolwe/flow/executors/null/run.py
resolwe/flow/expression_engines/__init__.py
resolwe/flow/expression_engines/base.py
resolwe-45.0.3.dist-info/licenses/LICENSE
resolwe-45.0.3.dist-info/METADATA
resolwe-45.0.3.dist-info/WHEEL
resolwe-45.0.3.dist-info/top_level.txt
resolwe-45.0.3.dist-info/RECORD
