Metadata-Version: 2.4
Name: resolwe
Version: 45.0.3
Summary: Open source enterprise dataflow engine in Django
Author-email: "Genialis, Inc" <dev-team@genialis.com>
License: Apache License (2.0)
Project-URL: Homepage, https://github.com/genialis/resolwe/
Project-URL: Documentation, https://resolwe.readthedocs.io/en/latest/
Project-URL: Repository, https://github.com/genialis/resolwe/
Keywords: resolwe,dataflow,django
Classifier: Development Status :: 5 - Production/Stable
Classifier: Environment :: Web Environment
Classifier: Framework :: Django
Classifier: Intended Audience :: Developers
Classifier: Topic :: Internet :: WWW/HTTP
Classifier: Topic :: Internet :: WWW/HTTP :: Dynamic Content
Classifier: Topic :: Internet :: WWW/HTTP :: HTTP Servers
Classifier: Topic :: Software Development :: Libraries :: Application Frameworks
Classifier: Topic :: Software Development :: Libraries :: Python Modules
Classifier: License :: OSI Approved :: Apache Software License
Classifier: Operating System :: OS Independent
Classifier: Programming Language :: Python
Classifier: Programming Language :: Python :: 3
Classifier: Programming Language :: Python :: 3.12
Classifier: Programming Language :: Python :: 3.13
Requires-Python: <3.14,>=3.12
License-File: LICENSE
Requires-Dist: asgiref~=3.8.1
Requires-Dist: asteval==1.0.6
Requires-Dist: beautifulsoup4~=4.13.3
Requires-Dist: channels~=4.2.2
Requires-Dist: channels_redis~=4.2.1
Requires-Dist: crcmod
Requires-Dist: Django~=5.2.0
Requires-Dist: django-fernet-fields-v2~=0.9
Requires-Dist: django-filter~=25.1
Requires-Dist: djangorestframework~=3.16.0
Requires-Dist: docker~=7.1.0
Requires-Dist: drf-spectacular~=0.28.0
Requires-Dist: Jinja2~=3.1.6
Requires-Dist: jsonschema~=4.23.0
Requires-Dist: kubernetes~=32.0.1
Requires-Dist: opentelemetry-api~=1.31.1
Requires-Dist: opentelemetry-exporter-otlp~=1.31.1
Requires-Dist: opentelemetry-sdk~=1.31.1
Requires-Dist: plumbum~=1.9.0
Requires-Dist: psycopg[binary]~=3.2.6
Requires-Dist: python-decouple~=3.8
Requires-Dist: pytz~=2025.2
Requires-Dist: PyYAML~=6.0.2
Requires-Dist: pyzmq~=26.3.0
Requires-Dist: redis~=5.2.1
Requires-Dist: shellescape~=3.8.1
Requires-Dist: Sphinx~=8.2.3
Requires-Dist: uvloop~=0.21.0
Requires-Dist: wrapt~=1.17.2
Provides-Extra: storage-s3
Requires-Dist: boto3~=1.37.25; extra == "storage-s3"
Requires-Dist: crcmod~=1.7; extra == "storage-s3"
Provides-Extra: storage-gcs
Requires-Dist: crcmod~=1.7; extra == "storage-gcs"
Requires-Dist: google-cloud-storage~=3.1.0; extra == "storage-gcs"
Provides-Extra: docs
Requires-Dist: sphinx_rtd_theme~=3.0.2; extra == "docs"
Requires-Dist: pyasn1>=0.6.1; extra == "docs"
Requires-Dist: daphne>=4.1.2; extra == "docs"
Provides-Extra: package
Requires-Dist: twine~=6.1.0; extra == "package"
Requires-Dist: wheel~=0.45.1; extra == "package"
Provides-Extra: test
Requires-Dist: black>=25.1.0; extra == "test"
Requires-Dist: check-manifest>=0.50; extra == "test"
Requires-Dist: coverage>=7.8.0; extra == "test"
Requires-Dist: daphne>=4.1.2; extra == "test"
Requires-Dist: django-filter-stubs>=0.1.3; extra == "test"
Requires-Dist: django-stubs>=5.1.3; extra == "test"
Requires-Dist: djangorestframework-stubs[compatible-mypy]>=3.15.3; extra == "test"
Requires-Dist: flake8>=7.2.0; extra == "test"
Requires-Dist: isort>=6.0.1; extra == "test"
Requires-Dist: mypy>=1.15.0; extra == "test"
Requires-Dist: pydocstyle>=6.3.0; extra == "test"
Requires-Dist: readme_renderer; extra == "test"
Requires-Dist: setuptools_scm; extra == "test"
Requires-Dist: tblib>=3.1.0; extra == "test"
Requires-Dist: testfixtures>=8.3.0; extra == "test"
Requires-Dist: twine~=6.1.0; extra == "test"
Requires-Dist: types-setuptools; extra == "test"
Dynamic: license-file
